async_sqs_consumer/__init__.py
async_sqs_consumer/py.typed
async_sqs_consumer/queue.py
async_sqs_consumer/resources.py
async_sqs_consumer/types.py
async_sqs_consumer/utils/__init__.py
async_sqs_consumer/utils/retry.py
async_sqs_consumer/worker.py
async_sqs_consumer-1.0.2.dist-info/METADATA
async_sqs_consumer-1.0.2.dist-info/WHEEL
async_sqs_consumer-1.0.2.dist-info/RECORD
