Metadata-Version: 2.1
Name: async_sqs_consumer
Version: 1.0.2
Summary: 
Home-page: https://github.com/drestrepom/async_sqs_consumer
Keywords: AWS,AWS,SQS,sqs,consumer,async,worker
Author: Diego Restrepo
Author-email: drestrepo@fluidattacks.com
Requires-Python: >=3.9,<4.0
Classifier: Programming Language :: Python :: 3
Classifier: Programming Language :: Python :: 3.9
Classifier: Programming Language :: Python :: 3.10
Classifier: Programming Language :: Python :: 3.11
Classifier: Programming Language :: Python :: 3.12
Classifier: Programming Language :: Python :: 3.13
Requires-Dist: aioboto3 (>=13.0.0,<14.0.0)
Requires-Dist: aiobotocore (>=2.0.0,<3.0.0)
Requires-Dist: aiohttp (>=3.9.2,<4.0.0)
Requires-Dist: jsonschema (>=4.17.3,<5.0.0)
Requires-Dist: pyrate-limiter (>=2.10.0,<3.0.0)
Requires-Dist: pytz (>=2023.3,<2024.0)
Project-URL: Repository, https://github.com/drestrepom/async_sqs_consumer
